fastpelt/__init__.py
fastpelt/fastpeltrust.cpython-37m-x86_64-linux-gnu.so
fastpelt/fastpeltrust.cpython-36m-x86_64-linux-gnu.so
fastpelt-0.1.1.dist-info/METADATA
fastpelt-0.1.1.dist-info/RECORD
fastpelt-0.1.1.dist-info/top_level.txt
fastpelt-0.1.1.dist-info/WHEEL
