Metadata-Version: 2.1
Name: fastpelt
Version: 0.1.1
Summary: UNKNOWN
Home-page: UNKNOWN
Author: Ritchie Vink
Author-email: ritchie46@gmail.com
License: UNKNOWN
Platform: UNKNOWN
Requires-Dist: numpy
